robosoc2d.cp38-win32.pyd
robosoc2d-1.0.0.dist-info/LICENSE
robosoc2d-1.0.0.dist-info/METADATA
robosoc2d-1.0.0.dist-info/WHEEL
robosoc2d-1.0.0.dist-info/top_level.txt
robosoc2d-1.0.0.dist-info/RECORD
