Metadata-Version: 2.1
Name: robosoc2d
Version: 1.0.0
Summary: Very Simplified 2D Robotic Soccer Simulator
Home-page: https://www.github.com/rug/robosoc2d
Author: Ruggero Rossi
Author-email: r.rossi@opencomplexity.com
License: UNKNOWN
Platform: UNKNOWN
License-File: LICENSE
